__init__.py
acceptance_calculator.py
acceptance_reader.py
prec_acceptances_data/__init__.py
prec_acceptances_data/v1/acceptances_13TeV.json
prec_acceptances_data/v1/acceptances_7TeV.json
prec_acceptances_data/v1/acceptances_8TeV.json
rx_prec_accepance-0.0.6.data/scripts/add_energy
rx_prec_accepance-0.0.6.data/scripts/calculate_acceptances
rx_prec_accepance-0.0.6.data/scripts/make_tuples
rx_prec_accepance-0.0.6.dist-info/METADATA
rx_prec_accepance-0.0.6.dist-info/WHEEL
rx_prec_accepance-0.0.6.dist-info/top_level.txt
rx_prec_accepance-0.0.6.dist-info/RECORD
