Metadata-Version: 2.1
Name: rx_prec_accepance
Version: 0.0.6
Summary: Scripts used to calculate acceptance for rare PRec decays
